[
{"time":"2017-08-02 16:00:00", "name":"201708021600.jpg", "url":"http://www.gdwater.gov.cn:9001/DataImage/Cloud/风云二号/201708/201708021600.jpg"},
{"time":"2017-08-02 16:15:00", "name":"201708021615.jpg", "url":"http://www.gdwater.gov.cn:9001/DataImage/Cloud/风云二号/201708/201708021615.jpg"},
{"time":"2017-08-02 16:30:00", "name":"201708021630.jpg", "url":"http://www.gdwater.gov.cn:9001/DataImage/Cloud/风云二号/201708/201708021630.jpg"},
{"time":"2017-08-02 16:45:00", "name":"201708021645.jpg", "url":"http://www.gdwater.gov.cn:9001/DataImage/Cloud/风云二号/201708/201708021645.jpg"},
{"time":"2017-08-02 17:00:00", "name":"201708021700.jpg", "url":"http://www.gdwater.gov.cn:9001/DataImage/Cloud/风云二号/201708/201708021700.jpg"},
{"time":"2017-08-02 17:15:00", "name":"201708021715.jpg", "url":"http://www.gdwater.gov.cn:9001/DataImage/Cloud/风云二号/201708/201708021715.jpg"},
{"time":"2017-08-02 17:30:00", "name":"201708021730.jpg", "url":"http://www.gdwater.gov.cn:9001/DataImage/Cloud/风云二号/201708/201708021730.jpg"},
{"time":"2017-08-02 17:45:00", "name":"201708021745.jpg", "url":"http://www.gdwater.gov.cn:9001/DataImage/Cloud/风云二号/201708/201708021745.jpg"},
{"time":"2017-08-02 18:00:00", "name":"201708021800.jpg", "url":"http://www.gdwater.gov.cn:9001/DataImage/Cloud/风云二号/201708/201708021800.jpg"},
{"time":"2017-08-02 18:15:00", "name":"201708021815.jpg", "url":"http://www.gdwater.gov.cn:9001/DataImage/Cloud/风云二号/201708/201708021815.jpg"},
{"time":"2017-08-02 18:30:00", "name":"201708021830.jpg", "url":"http://www.gdwater.gov.cn:9001/DataImage/Cloud/风云二号/201708/201708021830.jpg"},
{"time":"2017-08-02 18:45:00", "name":"201708021845.jpg", "url":"http://www.gdwater.gov.cn:9001/DataImage/Cloud/风云二号/201708/201708021845.jpg"},
{"time":"2017-08-02 19:00:00", "name":"201708021900.jpg", "url":"http://www.gdwater.gov.cn:9001/DataImage/Cloud/风云二号/201708/201708021900.jpg"},
{"time":"2017-08-02 19:15:00", "name":"201708021915.jpg", "url":"http://www.gdwater.gov.cn:9001/DataImage/Cloud/风云二号/201708/201708021915.jpg"},
{"time":"2017-08-02 19:30:00", "name":"201708021930.jpg", "url":"http://www.gdwater.gov.cn:9001/DataImage/Cloud/风云二号/201708/201708021930.jpg"},
{"time":"2017-08-02 19:45:00", "name":"201708021945.jpg", "url":"http://www.gdwater.gov.cn:9001/DataImage/Cloud/风云二号/201708/201708021945.jpg"},
{"time":"2017-08-02 20:00:00", "name":"201708022000.jpg", "url":"http://www.gdwater.gov.cn:9001/DataImage/Cloud/风云二号/201708/201708022000.jpg"},
{"time":"2017-08-02 20:15:00", "name":"201708022015.jpg", "url":"http://www.gdwater.gov.cn:9001/DataImage/Cloud/风云二号/201708/201708022015.jpg"},
{"time":"2017-08-02 20:30:00", "name":"201708022030.jpg", "url":"http://www.gdwater.gov.cn:9001/DataImage/Cloud/风云二号/201708/201708022030.jpg"},
{"time":"2017-08-02 20:45:00", "name":"201708022045.jpg", "url":"http://www.gdwater.gov.cn:9001/DataImage/Cloud/风云二号/201708/201708022045.jpg"},
{"time":"2017-08-02 21:00:00", "name":"201708022100.jpg", "url":"http://www.gdwater.gov.cn:9001/DataImage/Cloud/风云二号/201708/201708022100.jpg"},
{"time":"2017-08-02 21:15:00", "name":"201708022115.jpg", "url":"http://www.gdwater.gov.cn:9001/DataImage/Cloud/风云二号/201708/201708022115.jpg"},
{"time":"2017-08-02 21:30:00", "name":"201708022130.jpg", "url":"http://www.gdwater.gov.cn:9001/DataImage/Cloud/风云二号/201708/201708022130.jpg"},
{"time":"2017-08-02 21:45:00", "name":"201708022145.jpg", "url":"http://www.gdwater.gov.cn:9001/DataImage/Cloud/风云二号/201708/201708022145.jpg"},
{"time":"2017-08-02 22:00:00", "name":"201708022200.jpg", "url":"http://www.gdwater.gov.cn:9001/DataImage/Cloud/风云二号/201708/201708022200.jpg"},
{"time":"2017-08-02 22:15:00", "name":"201708022215.jpg", "url":"http://www.gdwater.gov.cn:9001/DataImage/Cloud/风云二号/201708/201708022215.jpg"},
{"time":"2017-08-02 22:30:00", "name":"201708022230.jpg", "url":"http://www.gdwater.gov.cn:9001/DataImage/Cloud/风云二号/201708/201708022230.jpg"},
{"time":"2017-08-02 22:45:00", "name":"201708022245.jpg", "url":"http://www.gdwater.gov.cn:9001/DataImage/Cloud/风云二号/201708/201708022245.jpg"},
{"time":"2017-08-02 23:00:00", "name":"201708022300.jpg", "url":"http://www.gdwater.gov.cn:9001/DataImage/Cloud/风云二号/201708/201708022300.jpg"},
{"time":"2017-08-02 23:15:00", "name":"201708022315.jpg", "url":"http://www.gdwater.gov.cn:9001/DataImage/Cloud/风云二号/201708/201708022315.jpg"},
{"time":"2017-08-02 23:30:00", "name":"201708022330.jpg", "url":"http://www.gdwater.gov.cn:9001/DataImage/Cloud/风云二号/201708/201708022330.jpg"},
{"time":"2017-08-02 23:45:00", "name":"201708022345.jpg", "url":"http://www.gdwater.gov.cn:9001/DataImage/Cloud/风云二号/201708/201708022345.jpg"},
{"time":"2017-08-03 00:00:00", "name":"201708030000.jpg", "url":"http://www.gdwater.gov.cn:9001/DataImage/Cloud/风云二号/201708/201708030000.jpg"},
{"time":"2017-08-03 00:15:00", "name":"201708030015.jpg", "url":"http://www.gdwater.gov.cn:9001/DataImage/Cloud/风云二号/201708/201708030015.jpg"},
{"time":"2017-08-03 00:30:00", "name":"201708030030.jpg", "url":"http://www.gdwater.gov.cn:9001/DataImage/Cloud/风云二号/201708/201708030030.jpg"},
{"time":"2017-08-03 00:45:00", "name":"201708030045.jpg", "url":"http://www.gdwater.gov.cn:9001/DataImage/Cloud/风云二号/201708/201708030045.jpg"},
{"time":"2017-08-03 01:00:00", "name":"201708030100.jpg", "url":"http://www.gdwater.gov.cn:9001/DataImage/Cloud/风云二号/201708/201708030100.jpg"},
{"time":"2017-08-03 01:15:00", "name":"201708030115.jpg", "url":"http://www.gdwater.gov.cn:9001/DataImage/Cloud/风云二号/201708/201708030115.jpg"},
{"time":"2017-08-03 01:30:00", "name":"201708030130.jpg", "url":"http://www.gdwater.gov.cn:9001/DataImage/Cloud/风云二号/201708/201708030130.jpg"},
{"time":"2017-08-03 01:45:00", "name":"201708030145.jpg", "url":"http://www.gdwater.gov.cn:9001/DataImage/Cloud/风云二号/201708/201708030145.jpg"},
{"time":"2017-08-03 02:00:00", "name":"201708030200.jpg", "url":"http://www.gdwater.gov.cn:9001/DataImage/Cloud/风云二号/201708/201708030200.jpg"},
{"time":"2017-08-03 02:15:00", "name":"201708030215.jpg", "url":"http://www.gdwater.gov.cn:9001/DataImage/Cloud/风云二号/201708/201708030215.jpg"},
{"time":"2017-08-03 02:30:00", "name":"201708030230.jpg", "url":"http://www.gdwater.gov.cn:9001/DataImage/Cloud/风云二号/201708/201708030230.jpg"},
{"time":"2017-08-03 02:45:00", "name":"201708030245.jpg", "url":"http://www.gdwater.gov.cn:9001/DataImage/Cloud/风云二号/201708/201708030245.jpg"},
{"time":"2017-08-03 03:00:00", "name":"201708030300.jpg", "url":"http://www.gdwater.gov.cn:9001/DataImage/Cloud/风云二号/201708/201708030300.jpg"},
{"time":"2017-08-03 03:15:00", "name":"201708030315.jpg", "url":"http://www.gdwater.gov.cn:9001/DataImage/Cloud/风云二号/201708/201708030315.jpg"},
{"time":"2017-08-03 03:30:00", "name":"201708030330.jpg", "url":"http://www.gdwater.gov.cn:9001/DataImage/Cloud/风云二号/201708/201708030330.jpg"},
{"time":"2017-08-03 03:45:00", "name":"201708030345.jpg", "url":"http://www.gdwater.gov.cn:9001/DataImage/Cloud/风云二号/201708/201708030345.jpg"},
{"time":"2017-08-03 04:00:00", "name":"201708030400.jpg", "url":"http://www.gdwater.gov.cn:9001/DataImage/Cloud/风云二号/201708/201708030400.jpg"},
{"time":"2017-08-03 04:15:00", "name":"201708030415.jpg", "url":"http://www.gdwater.gov.cn:9001/DataImage/Cloud/风云二号/201708/201708030415.jpg"},
{"time":"2017-08-03 04:30:00", "name":"201708030430.jpg", "url":"http://www.gdwater.gov.cn:9001/DataImage/Cloud/风云二号/201708/201708030430.jpg"},
{"time":"2017-08-03 04:45:00", "name":"201708030445.jpg", "url":"http://www.gdwater.gov.cn:9001/DataImage/Cloud/风云二号/201708/201708030445.jpg"},
{"time":"2017-08-03 05:00:00", "name":"201708030500.jpg", "url":"http://www.gdwater.gov.cn:9001/DataImage/Cloud/风云二号/201708/201708030500.jpg"},
{"time":"2017-08-03 05:15:00", "name":"201708030515.jpg", "url":"http://www.gdwater.gov.cn:9001/DataImage/Cloud/风云二号/201708/201708030515.jpg"},
{"time":"2017-08-03 05:30:00", "name":"201708030530.jpg", "url":"http://www.gdwater.gov.cn:9001/DataImage/Cloud/风云二号/201708/201708030530.jpg"},
{"time":"2017-08-03 05:45:00", "name":"201708030545.jpg", "url":"http://www.gdwater.gov.cn:9001/DataImage/Cloud/风云二号/201708/201708030545.jpg"},
{"time":"2017-08-03 06:00:00", "name":"201708030600.jpg", "url":"http://www.gdwater.gov.cn:9001/DataImage/Cloud/风云二号/201708/201708030600.jpg"},
{"time":"2017-08-03 06:15:00", "name":"201708030615.jpg", "url":"http://www.gdwater.gov.cn:9001/DataImage/Cloud/风云二号/201708/201708030615.jpg"},
{"time":"2017-08-03 06:30:00", "name":"201708030630.jpg", "url":"http://www.gdwater.gov.cn:9001/DataImage/Cloud/风云二号/201708/201708030630.jpg"},
{"time":"2017-08-03 06:45:00", "name":"201708030645.jpg", "url":"http://www.gdwater.gov.cn:9001/DataImage/Cloud/风云二号/201708/201708030645.jpg"},
{"time":"2017-08-03 07:00:00", "name":"201708030700.jpg", "url":"http://www.gdwater.gov.cn:9001/DataImage/Cloud/风云二号/201708/201708030700.jpg"},
{"time":"2017-08-03 07:15:00", "name":"201708030715.jpg", "url":"http://www.gdwater.gov.cn:9001/DataImage/Cloud/风云二号/201708/201708030715.jpg"},
{"time":"2017-08-03 07:30:00", "name":"201708030730.jpg", "url":"http://www.gdwater.gov.cn:9001/DataImage/Cloud/风云二号/201708/201708030730.jpg"},
{"time":"2017-08-03 07:45:00", "name":"201708030745.jpg", "url":"http://www.gdwater.gov.cn:9001/DataImage/Cloud/风云二号/201708/201708030745.jpg"},
{"time":"2017-08-03 08:00:00", "name":"201708030800.jpg", "url":"http://www.gdwater.gov.cn:9001/DataImage/Cloud/风云二号/201708/201708030800.jpg"},
{"time":"2017-08-03 08:15:00", "name":"201708030815.jpg", "url":"http://www.gdwater.gov.cn:9001/DataImage/Cloud/风云二号/201708/201708030815.jpg"},
{"time":"2017-08-03 08:30:00", "name":"201708030830.jpg", "url":"http://www.gdwater.gov.cn:9001/DataImage/Cloud/风云二号/201708/201708030830.jpg"},
{"time":"2017-08-03 08:45:00", "name":"201708030845.jpg", "url":"http://www.gdwater.gov.cn:9001/DataImage/Cloud/风云二号/201708/201708030845.jpg"},
{"time":"2017-08-03 09:00:00", "name":"201708030900.jpg", "url":"http://www.gdwater.gov.cn:9001/DataImage/Cloud/风云二号/201708/201708030900.jpg"},
{"time":"2017-08-03 09:15:00", "name":"201708030915.jpg", "url":"http://www.gdwater.gov.cn:9001/DataImage/Cloud/风云二号/201708/201708030915.jpg"},
{"time":"2017-08-03 09:30:00", "name":"201708030930.jpg", "url":"http://www.gdwater.gov.cn:9001/DataImage/Cloud/风云二号/201708/201708030930.jpg"},
{"time":"2017-08-03 09:45:00", "name":"201708030945.jpg", "url":"http://www.gdwater.gov.cn:9001/DataImage/Cloud/风云二号/201708/201708030945.jpg"},
{"time":"2017-08-03 10:00:00", "name":"201708031000.jpg", "url":"http://www.gdwater.gov.cn:9001/DataImage/Cloud/风云二号/201708/201708031000.jpg"},
{"time":"2017-08-03 10:15:00", "name":"201708031015.jpg", "url":"http://www.gdwater.gov.cn:9001/DataImage/Cloud/风云二号/201708/201708031015.jpg"},
{"time":"2017-08-03 10:30:00", "name":"201708031030.jpg", "url":"http://www.gdwater.gov.cn:9001/DataImage/Cloud/风云二号/201708/201708031030.jpg"},
{"time":"2017-08-03 10:45:00", "name":"201708031045.jpg", "url":"http://www.gdwater.gov.cn:9001/DataImage/Cloud/风云二号/201708/201708031045.jpg"},
{"time":"2017-08-03 11:00:00", "name":"201708031100.jpg", "url":"http://www.gdwater.gov.cn:9001/DataImage/Cloud/风云二号/201708/201708031100.jpg"},
{"time":"2017-08-03 11:15:00", "name":"201708031115.jpg", "url":"http://www.gdwater.gov.cn:9001/DataImage/Cloud/风云二号/201708/201708031115.jpg"},
{"time":"2017-08-03 11:30:00", "name":"201708031130.jpg", "url":"http://www.gdwater.gov.cn:9001/DataImage/Cloud/风云二号/201708/201708031130.jpg"},
{"time":"2017-08-03 11:45:00", "name":"201708031145.jpg", "url":"http://www.gdwater.gov.cn:9001/DataImage/Cloud/风云二号/201708/201708031145.jpg"},
{"time":"2017-08-03 12:00:00", "name":"201708031200.jpg", "url":"http://www.gdwater.gov.cn:9001/DataImage/Cloud/风云二号/201708/201708031200.jpg"},
{"time":"2017-08-03 12:15:00", "name":"201708031215.jpg", "url":"http://www.gdwater.gov.cn:9001/DataImage/Cloud/风云二号/201708/201708031215.jpg"},
{"time":"2017-08-03 12:30:00", "name":"201708031230.jpg", "url":"http://www.gdwater.gov.cn:9001/DataImage/Cloud/风云二号/201708/201708031230.jpg"},
{"time":"2017-08-03 12:45:00", "name":"201708031245.jpg", "url":"http://www.gdwater.gov.cn:9001/DataImage/Cloud/风云二号/201708/201708031245.jpg"},
{"time":"2017-08-03 13:00:00", "name":"201708031300.jpg", "url":"http://www.gdwater.gov.cn:9001/DataImage/Cloud/风云二号/201708/201708031300.jpg"},
{"time":"2017-08-03 13:15:00", "name":"201708031315.jpg", "url":"http://www.gdwater.gov.cn:9001/DataImage/Cloud/风云二号/201708/201708031315.jpg"},
{"time":"2017-08-03 13:30:00", "name":"201708031330.jpg", "url":"http://www.gdwater.gov.cn:9001/DataImage/Cloud/风云二号/201708/201708031330.jpg"},
{"time":"2017-08-03 13:45:00", "name":"201708031345.jpg", "url":"http://www.gdwater.gov.cn:9001/DataImage/Cloud/风云二号/201708/201708031345.jpg"},
{"time":"2017-08-03 14:00:00", "name":"201708031400.jpg", "url":"http://www.gdwater.gov.cn:9001/DataImage/Cloud/风云二号/201708/201708031400.jpg"},
{"time":"2017-08-03 14:15:00", "name":"201708031415.jpg", "url":"http://www.gdwater.gov.cn:9001/DataImage/Cloud/风云二号/201708/201708031415.jpg"},
{"time":"2017-08-03 14:30:00", "name":"201708031430.jpg", "url":"http://www.gdwater.gov.cn:9001/DataImage/Cloud/风云二号/201708/201708031430.jpg"},
{"time":"2017-08-03 14:45:00", "name":"201708031445.jpg", "url":"http://www.gdwater.gov.cn:9001/DataImage/Cloud/风云二号/201708/201708031445.jpg"},
{"time":"2017-08-03 15:00:00", "name":"201708031500.jpg", "url":"http://www.gdwater.gov.cn:9001/DataImage/Cloud/风云二号/201708/201708031500.jpg"},
{"time":"2017-08-03 15:15:00", "name":"201708031515.jpg", "url":"http://www.gdwater.gov.cn:9001/DataImage/Cloud/风云二号/201708/201708031515.jpg"},
{"time":"2017-08-03 15:30:00", "name":"201708031530.jpg", "url":"http://www.gdwater.gov.cn:9001/DataImage/Cloud/风云二号/201708/201708031530.jpg"}
]