{
  "success": true,
  "message": "分页查询成功",
  "content": {
    "pageNum": 1,
    "pageSize": 10,
    "size": 10,
    "startRow": 1,
    "endRow": 10,
    "total": 10,
    "pages": 1,
    "list": [
      {
        "rowId": 1,
        "qh": "天河",
        "zh":"01-01",
        "zm":"市三防",
        "jczb":"雨量",
        "CODE12":"C440100011",
        "hs":"",
        "azdz":"天河区五山街广园快速路广之旅大厦",
        "ssxt":"水文遥测",
        "sm":"",
        "x":45685.6,
        "y":31337.8
      },{
        "rowId": 2,
        "qh": "天河",
        "zh":"01-03",
        "zm":"龙洞水库",
        "jczb":"水位/雨量",
        "CODE12":"C440106031",
        "hs":"",
        "azdz":"天河区凤凰街渔沙坦村渔东路",
        "ssxt":"水文遥测",
        "sm":"",
        "x":50388.5,
        "y":39444.7
      },{
        "rowId": 3,
        "qh": "天河",
        "zh":"01-05",
        "zm":"深涌水闸",
        "jczb":"水位/雨量",
        "CODE12":"C440106011",
        "hs":"外",
        "azdz":"天河区前进街黄埔大道东深涌涌口",
        "ssxt":"水文遥测",
        "sm":"",
        "x":52965.3,
        "y":15281.1
      },{
        "rowId": 4,
        "qh": "天河",
        "zh":"01-05",
        "zm":"深涌水闸",
        "jczb":"水位",
        "CODE12":"C440106012",
        "hs":"内",
        "azdz":"天河区前进街黄埔大道东深涌涌口",
        "ssxt":"水文遥测",
        "sm":"",
        "x":52965.3,
        "y":15281.1
      },{
        "rowId": 5,
        "qh": "天河",
        "zh":"01-06",
        "zm":"猎德涌",
        "jczb":"水位",
        "CODE12":"C440106061",
        "hs":"外",
        "azdz":"天河区猎德街临江大道57号东南面",
        "ssxt":"水文遥测",
        "sm":"GPRS",
        "x":44143.1,
        "y":27734.8
      },{
        "rowId": 6,
        "qh": "天河",
        "zh":"01-06",
        "zm":"猎德涌",
        "jczb":"水位",
        "CODE12":"C440106062",
        "hs":"内",
        "azdz":"天河区猎德街临江大道57号东南面",
        "ssxt":"水文遥测",
        "sm":"GPRS",
        "x":44143.1,
        "y":27734.8
      },{
        "rowId": 7,
        "qh": "天河",
        "zh":"01-08",
        "zm":"车陂涌上",
        "jczb":"水位/雨量",
        "CODE12":"C440106081",
        "hs":"",
        "azdz":"天河区凤凰街广汕路广东树木公园",
        "ssxt":"水文遥测",
        "sm":"GPRS",
        "x":48680.2,
        "y":36485.5
      },{
        "rowId": 8,
        "qh": "天河",
        "zh":"01-09",
        "zm":"车陂旭景中",
        "jczb":"水位/雨量",
        "CODE12":"C440106091",
        "hs":"",
        "azdz":"天河区车陂街旭景西街",
        "ssxt":"水文遥测",
        "sm":"GPRS",
        "x":51554.1,
        "y":29166.9
      },{
        "rowId": 9,
        "qh": "天河",
        "zh":"01-010",
        "zm":"车陂涌口下",
        "jczb":"水位/雨量",
        "CODE12":"C440106101",
        "hs":"",
        "azdz":"天河区车陂街车陂新涌口东街",
        "ssxt":"水文遥测",
        "sm":"GPRS",
        "x":51224.4,
        "y":27158.3
      },{
        "rowId": 10,
        "qh": "天河",
        "zh":"01-11",
        "zm":"沙河涌上",
        "jczb":"水位/雨量",
        "CODE12":"C440106111",
        "hs":"",
        "azdz":"天河区兴华街银燕路兴华街办门口",
        "ssxt":"水文遥测",
        "sm":"GPRS",
        "x":32388.7,
        "y":56038.4
      }
    ],
    "firstPage": 1,
    "nextPage": 1,
    "lastPage": 1,
    "isFirstPage": true,
    "isLastPage": true,
    "hasPreviousPage": false,
    "hasNextPage": false,
    "navigatePages": 8,
    "navigatepageNums": [
      1
    ]
  }
}